Metadata-Version: 2.1
Name: outliers-101703192
Version: 0.0.1
Summary: A Simple Package to detect and remove outliers using Inter-Quatile Range
Home-page: UNKNOWN
Author: Girish Jullka
Author-email: girishjulka8@gmail.com
License: UNKNOWN
Platform: UNKNOWN
Classifier: Programming Language :: Python :: 3
Classifier: License :: OSI Approved :: MIT License
Classifier: Operating System :: OS Independent
Requires-Python: >=3.6
